README
setup.cfg
setup.py
lava/__init__.py
lava/builder/__init__.py
lava/builder/interface.py
lava/builder/simple.py
lava/fastmodels/__init__.py
lava/fastmodels/commands.py
lava/fastmodels/models.py
lava/fastmodels/simulators.py
lava/nfs/__init__.py
lava/nfs/backend.py
lava/nfs/commands.py
lava/nfs/tests.py
lava_fastmodels.egg-info/PKG-INFO
lava_fastmodels.egg-info/SOURCES.txt
lava_fastmodels.egg-info/dependency_links.txt
lava_fastmodels.egg-info/entry_points.txt
lava_fastmodels.egg-info/namespace_packages.txt
lava_fastmodels.egg-info/requires.txt
lava_fastmodels.egg-info/top_level.txt
lava_fastmodels.egg-info/zip-safe